{
  "parent": "minecraft:essence/obtain_essence_mooshroom",
  "display": {
    "icon": {
      "item": "mohard:essence_mule"
    },
    "title": {
      "translate": "advancements.essence.mule"
    },
    "description": {
      "translate": "advancements.essence.mule.description"
    },
    "frame": "task",
    "show_toast": false,
    "announce_to_chat": false,
    "hidden": false
  },
  "criteria": {
    "essence_mule": {
      "trigger": "minecraft:inventory_changed",
      "conditions": {
        "items": [
          {
            "items": [
              "mohard:essence_mule"
            ]
          }
        ]
      }
    }
  },
  "requirements": [
    [
      "essence_mule"
    ]
  ]
}